SolarAge/SolarAge.py
SolarAge/__init__.py
SolarAge-0.0.2.dist-info/LICENSE
SolarAge-0.0.2.dist-info/METADATA
SolarAge-0.0.2.dist-info/WHEEL
SolarAge-0.0.2.dist-info/top_level.txt
SolarAge-0.0.2.dist-info/RECORD
