Metadata-Version: 2.2
Name: SolarAge
Version: 0.0.2
Summary: A Python package for calculating and converting Persian, Islamic, and Gregorian dates, along with zodiac signs, animal years, birthstones, and age calculations based on the Persian calendar.
Author-email: Ali Ayati Qaffari <ayatiali910@gmail.com>
License: MIT License
Project-URL: Profile, https://github.com/MrAAQPy
Project-URL: github, https://github.com/MrAAQPy/SolarAge
Project-URL: issue, https://github.com/MrAAQPy/SolarAge/issues
Project-URL: bale, https://ble.ir/aaq1386
Requires-Python: >=3.7
License-File: LICENSE
Requires-Dist: jdatetime
Requires-Dist: convertdate
